<?xml version="1.0" encoding="UTF-8"?>
<entity-facade-xml type="seed">
    <moqui.basic.Geo geoId="HN-AT" geoName="Atlántida" abbreviation="HN-AT" geoCodeAlpha2="HN-AT" geoAssocTypeEnumId="GEOT_STATE"/>
    <moqui.basic.Geo geoId="HN-CH" geoName="Choluteca" abbreviation="HN-CH" geoCodeAlpha2="HN-CH" geoAssocTypeEnumId="GEOT_STATE"/>
    <moqui.basic.Geo geoId="HN-CL" geoName="Colón" abbreviation="HN-CL" geoCodeAlpha2="HN-CL" geoAssocTypeEnumId="GEOT_STATE"/>
    <moqui.basic.Geo geoId="HN-CM" geoName="Comayagua" abbreviation="HN-CM" geoCodeAlpha2="HN-CM" geoAssocTypeEnumId="GEOT_STATE"/>
    <moqui.basic.Geo geoId="HN-CP" geoName="Copán" abbreviation="HN-CP" geoCodeAlpha2="HN-CP" geoAssocTypeEnumId="GEOT_STATE"/>
    <moqui.basic.Geo geoId="HN-CR" geoName="Cortés" abbreviation="HN-CR" geoCodeAlpha2="HN-CR" geoAssocTypeEnumId="GEOT_STATE"/>
    <moqui.basic.Geo geoId="HN-EP" geoName="El Paraíso" abbreviation="HN-EP" geoCodeAlpha2="HN-EP" geoAssocTypeEnumId="GEOT_STATE"/>
    <moqui.basic.Geo geoId="HN-FM" geoName="Francisco Morazán" abbreviation="HN-FM" geoCodeAlpha2="HN-FM" geoAssocTypeEnumId="GEOT_STATE"/>
    <moqui.basic.Geo geoId="HN-GD" geoName="Gracias a Dios" abbreviation="HN-GD" geoCodeAlpha2="HN-GD" geoAssocTypeEnumId="GEOT_STATE"/>
    <moqui.basic.Geo geoId="HN-IN" geoName="Intibucá" abbreviation="HN-IN" geoCodeAlpha2="HN-IN" geoAssocTypeEnumId="GEOT_STATE"/>
    <moqui.basic.Geo geoId="HN-IB" geoName="Islas de la Bahía" abbreviation="HN-IB" geoCodeAlpha2="HN-IB" geoAssocTypeEnumId="GEOT_STATE"/>
    <moqui.basic.Geo geoId="HN-LP" geoName="La Paz" abbreviation="HN-LP" geoCodeAlpha2="HN-LP" geoAssocTypeEnumId="GEOT_STATE"/>
    <moqui.basic.Geo geoId="HN-LE" geoName="Lempira" abbreviation="HN-LE" geoCodeAlpha2="HN-LE" geoAssocTypeEnumId="GEOT_STATE"/>
    <moqui.basic.Geo geoId="HN-OC" geoName="Ocotepeque" abbreviation="HN-OC" geoCodeAlpha2="HN-OC" geoAssocTypeEnumId="GEOT_STATE"/>
    <moqui.basic.Geo geoId="HN-OL" geoName="Olancho" abbreviation="HN-OL" geoCodeAlpha2="HN-OL" geoAssocTypeEnumId="GEOT_STATE"/>
    <moqui.basic.Geo geoId="HN-SB" geoName="Santa Bárbara" abbreviation="HN-SB" geoCodeAlpha2="HN-SB" geoAssocTypeEnumId="GEOT_STATE"/>
    <moqui.basic.Geo geoId="HN-VA" geoName="Valle" abbreviation="HN-VA" geoCodeAlpha2="HN-VA" geoAssocTypeEnumId="GEOT_STATE"/>
    <moqui.basic.Geo geoId="HN-YO" geoName="Yoro" abbreviation="HN-YO" geoCodeAlpha2="HN-YO" geoAssocTypeEnumId="GEOT_STATE"/>
    <moqui.basic.GeoAssoc geoId="HND" toGeoId="HN-AT" geoAssocTypeEnumId="GAT_REGIONS"/>
    <moqui.basic.GeoAssoc geoId="HND" toGeoId="HN-CH" geoAssocTypeEnumId="GAT_REGIONS"/>
    <moqui.basic.GeoAssoc geoId="HND" toGeoId="HN-CL" geoAssocTypeEnumId="GAT_REGIONS"/>
    <moqui.basic.GeoAssoc geoId="HND" toGeoId="HN-CM" geoAssocTypeEnumId="GAT_REGIONS"/>
    <moqui.basic.GeoAssoc geoId="HND" toGeoId="HN-CP" geoAssocTypeEnumId="GAT_REGIONS"/>
    <moqui.basic.GeoAssoc geoId="HND" toGeoId="HN-CR" geoAssocTypeEnumId="GAT_REGIONS"/>
    <moqui.basic.GeoAssoc geoId="HND" toGeoId="HN-EP" geoAssocTypeEnumId="GAT_REGIONS"/>
    <moqui.basic.GeoAssoc geoId="HND" toGeoId="HN-FM" geoAssocTypeEnumId="GAT_REGIONS"/>
    <moqui.basic.GeoAssoc geoId="HND" toGeoId="HN-GD" geoAssocTypeEnumId="GAT_REGIONS"/>
    <moqui.basic.GeoAssoc geoId="HND" toGeoId="HN-IN" geoAssocTypeEnumId="GAT_REGIONS"/>
    <moqui.basic.GeoAssoc geoId="HND" toGeoId="HN-IB" geoAssocTypeEnumId="GAT_REGIONS"/>
    <moqui.basic.GeoAssoc geoId="HND" toGeoId="HN-LP" geoAssocTypeEnumId="GAT_REGIONS"/>
    <moqui.basic.GeoAssoc geoId="HND" toGeoId="HN-LE" geoAssocTypeEnumId="GAT_REGIONS"/>
    <moqui.basic.GeoAssoc geoId="HND" toGeoId="HN-OC" geoAssocTypeEnumId="GAT_REGIONS"/>
    <moqui.basic.GeoAssoc geoId="HND" toGeoId="HN-OL" geoAssocTypeEnumId="GAT_REGIONS"/>
    <moqui.basic.GeoAssoc geoId="HND" toGeoId="HN-SB" geoAssocTypeEnumId="GAT_REGIONS"/>
    <moqui.basic.GeoAssoc geoId="HND" toGeoId="HN-VA" geoAssocTypeEnumId="GAT_REGIONS"/>
    <moqui.basic.GeoAssoc geoId="HND" toGeoId="HN-YO" geoAssocTypeEnumId="GAT_REGIONS"/>
</entity-facade-xml>

